LICENSE
README.md
setup.cfg
setup.py
labtrade/labtrade.py
labtrade.egg-info/PKG-INFO
labtrade.egg-info/SOURCES.txt
labtrade.egg-info/dependency_links.txt
labtrade.egg-info/top_level.txt