Metadata-Version: 2.1
Name: labtrade
Version: 1.0.0
Summary: A visual tool to support the development of strategies in Quantitative Finance.
Home-page: https://github.com/fab2112/labtrade.git
Author: Fabrício Siqueira
Author-email: fabrisiqueira2112@gmail.com
License: MIT License
Keywords: Finance Quantitative Trade Tecnhical-Analyse Stock-Market Backtest
Platform: UNKNOWN
Classifier: Development Status :: 4 - Beta
Classifier: Intended Audience :: Science/Research
Classifier: License :: OSI Approved :: MIT License
Classifier: Natural Language :: Portuguese (Brazilian)
Classifier: Operating System :: OS Independent
Classifier: Topic :: Office/Business :: Financial :: Investment
Classifier: Topic :: Scientific/Engineering :: Information Analysis
Classifier: Topic :: Scientific/Engineering :: Artificial Intelligence
Classifier: Programming Language :: Python :: 3.9
License-File: LICENSE
